setup.cfg
setup.py
rtfd/__init__.py
rtfd/helpers.py
rtfd/rtfd.py
rtfd_cli.egg-info/PKG-INFO
rtfd_cli.egg-info/SOURCES.txt
rtfd_cli.egg-info/dependency_links.txt
rtfd_cli.egg-info/entry_points.txt
rtfd_cli.egg-info/requires.txt
rtfd_cli.egg-info/top_level.txt