Metadata-Version: 1.0
Name: rtfd-cli
Version: 0.1.2
Summary: CLI to download docs from ReadTheDocs.org
Home-page: https://github.com/MUSoC/rtfd-cli
Author: Nitanshu Vashistha
Author-email: nitanshu.vzard@gmail.com
License: MIT
Keywords: readthedocs,terminal,command-line,rtfd,python
Platform: UNKNOWN
